trymoieis/__init__.py
trymoieis/yuy.py
moieistryr-0.0.1.dist-info/METADATA
moieistryr-0.0.1.dist-info/WHEEL
moieistryr-0.0.1.dist-info/top_level.txt
moieistryr-0.0.1.dist-info/RECORD
